{
  "scraped_at": "2025-12-15T12:59:25.279889",
  "batch_number": 25,
  "character_count": 50,
  "characters": [
    {
      "source_name": "Kop",
      "source_url": "https://onepiece.fandom.com/wiki/Kop",
      "Japanese Name": "コップ",
      "Romanized Name": "Koppu",
      "Official English Name": "Kopp[1]",
      "Debut": "Chapter 325;Episode 231[2]",
      "Affiliations": "Franky Family",
      "Occupations": "Dismantler,Bounty Hunter",
      "Residence": "Water 7",
      "Status": "Alive",
      "Japanese Voice": "Unknown",
      "English Voice": "Funimation:Jeff Plunk"
    },
    {
      "source_name": "Kotetsu",
      "source_url": "https://onepiece.fandom.com/wiki/Kotetsu",
      "Japanese Name": "古徹",
      "Romanized Name": "Kotetsu",
      "Official English Name": "Kotetsu",
      "Debut": "Chapter 912;Episode 897(mentioned)[1]",
      "Occupations": "Swordsmith[1]",
      "Status": "Deceased"
    },
    {
      "source_name": "Kouzuki_Momonosuke",
      "source_url": "https://onepiece.fandom.com/wiki/Kouzuki_Momonosuke",
      "Japanese Name": "光月モモの助",
      "Romanized Name": "Kōzuki Momonosuke",
      "Official English Name": "Kozuki Momonosuke (VIZ); Kouzuki Momonosuke (WT100,OPCG)[1]",
      "Debut": "Chapter 684;Episode 609[2]",
      "Affiliations": "Kouzuki Family;[3]Ninja-Pirate-Mink-Samurai Alliance(disbanded)",
      "Occupations": "Shogun[4]",
      "Origin": "Grand Line(Moby Dick)[5]",
      "Residence": "Wano Country(Kuri);Flower Capital(Shogun Castle)[6]",
      "Status": "Alive",
      "Age": "8[7](born 28 years ago)(biologically 28)[8][N 1]",
      "Birthday": "October 7th[9]",
      "Height": "110 cm (3'7\") (child body)322 cm (10'7\") (current)[9]",
      "Blood Type": "X[9]",
      "Japanese Voice": "Ai Orikasa(young);Hiro Shimono(adult)",
      "English Voice": "Funimation:Corinne Sudberg (young);Justin Briner(adult)"
    },
    {
      "source_name": "Kouzuki_Sukiyaki",
      "source_url": "https://onepiece.fandom.com/wiki/Kouzuki_Sukiyaki",
      "Japanese Name": "光月スキヤキ",
      "Romanized Name": "Kōzuki Sukiyaki",
      "Official English Name": "Kozuki Sukiyaki",
      "Debut": "Chapter 911;Episode 894[1]",
      "Affiliations": "Kouzuki Family[3];Ninja-Pirate-Mink-Samurai Alliance(disbanded)",
      "Occupations": "Swordsmith;[2]Shogun(former)[3]",
      "Origin": "Grand Line(Wano Country)",
      "Residence": "Wano Country(Amigasa Village, formerlyFlower Capital)",
      "Alias": "\"Tenguyama Hitetsu\"(天狗山飛徹,Tenguyama Hitetsu?)",
      "Status": "Alive",
      "Age": "81[4]",
      "Birthday": "May 19th[4]",
      "Height": "214 cm (7'0\")[4]",
      "Blood Type": "F[4]",
      "Japanese Voice": "Ryūzaburō Ōtomo;[5]Reimi (baby)",
      "English Voice": "Funimation:John Burgmeier"
    },
    {
      "source_name": "Krieg",
      "source_url": "https://onepiece.fandom.com/wiki/Krieg",
      "Japanese Name": "クリーク",
      "Romanized Name": "Kurīku",
      "Official English Name": "Krieg",
      "Debut": "Chapter 45;Episode 21[1]",
      "Affiliations": "Krieg Pirates[2]",
      "Occupations": "Pirate Captain/Admiral[1]",
      "Origin": "East Blue[3]",
      "Epithet": "\"Don Krieg\"(首領・クリーク,Don Kurīku?);\"Pirate Fleet Admiral\"(海賊艦隊提督,Kaizoku Kantai Teitoku?)[4][5];\"Ruler of theEast Blue\"(東の海の覇者,Īsuto Burū no Hasha?)[6];\"Foul Play Krieg\"(ダマし討ちのクリーク,Damashi-uchi no Kurīku?)[6]",
      "Status": "Alive",
      "Age": "42 (debut)44 (after timeskip)[7]",
      "Birthday": "September 19th[8]",
      "Height": "243 cm (8'0\")[3]",
      "Blood Type": "XF[3]",
      "Bounty": "17,000,000[9]",
      "Japanese Voice": "Fumihiko Tachiki",
      "English Voice": "Odex:Jamie Meldrum4Kids:Marc ThompsonFunimation:Andy Mullins",
      "Live-Action Portrayal": "Milton Schorr"
    },
    {
      "source_name": "Kujaku",
      "source_url": "https://onepiece.fandom.com/wiki/Kujaku",
      "Japanese Name": "孔雀",
      "Romanized Name": "Kujaku",
      "Official English Name": "Kujaku;Kujyaku (OPCG)",
      "Debut": "Chapter 966(cover);[1]Episode 1090[2]",
      "Affiliations": "Marines(G-14);[1](SWORD)[2]",
      "Occupations": "Rear Admiral",
      "Origin": "North Blue[3]",
      "Residence": "G-14",
      "Status": "Alive",
      "Age": "26[4]",
      "Birthday": "September 18th[3]",
      "Height": "180 cm (5'11\")[4]",
      "Blood Type": "X[3]",
      "Bounty": "★★★★★ (500,000,000)[3]",
      "Japanese Voice": "Marina Inoue",
      "English Voice": "Funimation:Mallorie Rodak"
    },
    {
      "source_name": "Kumae",
      "source_url": "https://onepiece.fandom.com/wiki/Kumae",
      "Japanese Name": "くまエー",
      "Romanized Name": "Kumaē",
      "Official English Name": "Kuma-A",
      "Debut": "SBS Volume 66[1]",
      "Occupations": "Pet[1]",
      "Status": "Unknown"
    },
    {
      "source_name": "Kumashi",
      "source_url": "https://onepiece.fandom.com/wiki/Kumashi",
      "Japanese Name": "クマシー",
      "Romanized Name": "Kumashī",
      "Official English Name": "Kumacy",
      "Debut": "Chapter 449;Episode 343[1]",
      "Affiliations": "Thriller Bark Pirates(Perona)[2]",
      "Occupations": "Perona's servant;[2]Wild ZombieCommander-in-Chief[3]",
      "Status": "Deceased",
      "Birthday": "September 4th[4]",
      "Japanese Voice": "Hiroshi Iwasaki",
      "English Voice": "Funimation:Ray Hurd"
    },
    {
      "source_name": "Kunyun",
      "source_url": "https://onepiece.fandom.com/wiki/Kunyun",
      "Japanese Name": "九忍",
      "Romanized Name": "Kunyun",
      "Official English Name": "Kunyun",
      "Debut": "Chapter 1020;Episode 1042[1]",
      "Affiliations": "Beasts Pirates(Numbers)",
      "Residence": "Onigashima",
      "Status": "Alive",
      "Japanese Voice": "Hinako Takahashi",
      "English Voice": "Funimation:Dani Chambers"
    },
    {
      "source_name": "Kuro",
      "source_url": "https://onepiece.fandom.com/wiki/Kuro",
      "Japanese Name": "クロ",
      "Romanized Name": "Kuro",
      "Official English Name": "Kuro",
      "Debut": "Chapter 23;Episode 9[1]",
      "Affiliations": "Black Cat Pirates",
      "Occupations": "Pirate Captain(former); Butler (former)",
      "Origin": "East Blue[3]",
      "Residence": "Syrup Village(former)",
      "Alias": "\"Klahadore\"(クラハドール,Kurahadōru?,Odex: Klahadoll)",
      "Epithet": "\"Kuro of a Hundred Plans\"(百計のクロ,Hyakkei no Kuro?, English: \"Kuro of a Thousand Plans\")",
      "Status": "Alive",
      "Age": "33 (debut)35 (after timeskip)[2]",
      "Birthday": "April 22nd[4]",
      "Height": "207 cm (6’9”)[3]",
      "Blood Type": "X[3]",
      "Bounty": "16,000,000[5][6]",
      "Japanese Voice": "Kōichi Hashimoto",
      "English Voice": "Odex:Joseph Murray4Kids:Gary MackFunimation:Kent Williams",
      "Live-Action Portrayal": "Alexander Maniatis"
    },
    {
      "source_name": "Kuroobi",
      "source_url": "https://onepiece.fandom.com/wiki/Kuroobi",
      "Japanese Name": "クロオビ",
      "Romanized Name": "Kuro'obi",
      "Official English Name": "Kuroobi",
      "Debut": "Chapter 69;Episode 31[1]",
      "Affiliations": "Arlong Pirates;[2]Sun Pirates(former)[3]",
      "Occupations": "PirateOfficer[2]",
      "Origin": "Grand Line(Ryugu Kingdom,Fish-Man Island)",
      "Residence": "Fish-Man District(former);Arlong Park(former)",
      "Status": "Alive",
      "Age": "36 (debut)38 (after timeskip)[5]",
      "Birthday": "October 25th[4]",
      "Height": "252 cm (8'3\")[5]",
      "Blood Type": "S[5]",
      "Bounty": "9,000,000[5]",
      "Japanese Voice": "Hisao Egawa",
      "English Voice": "Odex:Jamie Meldrum4Kids:Sean SchemmelFunimation:Patrick Seitz"
    },
    {
      "source_name": "Kurotsuru",
      "source_url": "https://onepiece.fandom.com/wiki/Kurotsuru",
      "Japanese Name": "クロツル",
      "Romanized Name": "Kurotsuru",
      "Official English Name": "Blackbeard",
      "Debut": "Chapter 276(cover)[1]",
      "Occupations": "Doctor",
      "Status": "Unknown"
    },
    {
      "source_name": "Kyo",
      "source_url": "https://onepiece.fandom.com/wiki/Kyo",
      "Japanese Name": "凶",
      "Romanized Name": "Kyō",
      "Official English Name": "Kyo",
      "Debut": "Chapter 1156[1]",
      "Affiliations": "Rocks Pirates(former)[2]",
      "Occupations": "Pirate;[2]Hitman; Mobster(極道,Gokudō?)[1]",
      "Residence": "Hachinosu",
      "Epithet": "\"Silver Axe\"(銀斧,Ginbu?)[2]",
      "Status": "Unknown"
    },
    {
      "source_name": "Kyros",
      "source_url": "https://onepiece.fandom.com/wiki/Kyros",
      "Japanese Name": "キュロス",
      "Romanized Name": "Kyurosu",
      "Official English Name": "Kyros",
      "Debut": "Chapter 702;Episode 631[1]",
      "Affiliations": "Corrida Colosseum(former); Riku Royal Army",
      "Occupations": "Gladiator (former); Riku Royal Army Captain (former)",
      "Origin": "Grand Line(Dressrosa)[2]",
      "Alias": "\"Thunder Soldier of Rage\"(怒りの雷兵,Ikari no Kaminari Hei?, Viz: \"The Angry Lightning Soldier\");[3]\"The Invincible Gladiator\"",
      "Status": "Alive",
      "Age": "44[4][2]",
      "Birthday": "September 22nd[5]",
      "Height": "298 cm (9'9\")[2]",
      "Blood Type": "S[2]",
      "Bounty": "Unknown(as Thunder Soldier)[6]",
      "Japanese Voice": "Rikiya Koyama",
      "English Voice": "Funimation:Ivan Jasso"
    },
    {
      "source_name": "Kyukyu",
      "source_url": "https://onepiece.fandom.com/wiki/Kyukyu",
      "Japanese Name": "キューキュー",
      "Romanized Name": "Kyūkyū",
      "Official English Name": "Firstaid",
      "Debut": "Chapter 334;Episode 237[1]",
      "Occupations": "Doctor",
      "Residence": "Water 7",
      "Status": "Alive",
      "Japanese Voice": "Masaya Takatsuka"
    },
    {
      "source_name": "Laboon",
      "source_url": "https://onepiece.fandom.com/wiki/Laboon",
      "Japanese Name": "ラブーン",
      "Romanized Name": "Rabūn",
      "Official English Name": "Laboon;Raboon (Odex)",
      "Debut": "Chapter 102;Episode 62[1]",
      "Affiliations": "Rumbar Pirates(former);Crocus[2]",
      "Origin": "West Blue[3]",
      "Residence": "Reverse Mountain(Twin Cape)[1]",
      "Status": "Alive",
      "Age": "51 (debut)[2]53 (after timeskip)[3]",
      "Birthday": "September 16th[4]",
      "Height": "400 m (1312'4\")[5]",
      "Blood Type": "F[3]"
    },
    {
      "source_name": "Lacroix",
      "source_url": "https://onepiece.fandom.com/wiki/Lacroix",
      "Japanese Name": "ラクロワ",
      "Romanized Name": "Rakurowa",
      "Official English Name": "Lacroix",
      "Debut": "Chapter 550;Episode 459",
      "Affiliations": "Marines,Giant Squad",
      "Occupations": "Vice Admiral",
      "Status": "Alive",
      "Birthday": "June 8th[1]",
      "Bounty": "At least ★★★★★(At least500,000,000)[2]",
      "Japanese Voice": "Takahiro Yoshimizu",
      "English Voice": "Funimation:Brandon Luna"
    },
    {
      "source_name": "Lassoo",
      "source_url": "https://onepiece.fandom.com/wiki/Lassoo",
      "Japanese Name": "ラッスー",
      "Romanized Name": "Rassū",
      "Official English Name": "Lassoo",
      "Debut": "Chapter 160;Episode 103[1]",
      "Affiliations": "New Spiders Cafe;Baroque Works[1](former)",
      "Occupations": "Cafe Mascot;[2]Pet[1]",
      "Status": "Alive",
      "Birthday": "January 4th[3]",
      "Japanese Voice": "Masaya Takatsuka,Takeshi Aono(Movie 8),Koji Haramaki (Grand Battle! Rush!, Pirates' Carnival)",
      "English Voice": "4Kids:UnknownFunimation:Christopher Bevins"
    },
    {
      "source_name": "Lemoncheese",
      "source_url": "https://onepiece.fandom.com/wiki/Lemoncheese",
      "Japanese Name": "レモンチーズ",
      "Romanized Name": "Remonchīzu",
      "Official English Name": "Lemoncheese",
      "Debut": "Chapter 906;Episode 884[1]",
      "Affiliations": "Levely[2]",
      "Occupations": "Queenof the Bestland Kingdom[2]",
      "Residence": "Bestland Kingdom[3]",
      "Status": "Alive",
      "Japanese Voice": "Kimiko Saitō",
      "English Voice": "Funimation:Corey Pettit"
    },
    {
      "source_name": "Lines",
      "source_url": "https://onepiece.fandom.com/wiki/Lines",
      "Japanese Name": "ラインズ",
      "Romanized Name": "Rainzu",
      "Official English Name": "Lines",
      "Debut": "Chapter 44;Episode 21[1]",
      "Occupations": "Marine Seaman First Class",
      "Origin": "East Blue[2]",
      "Status": "Alive",
      "Birthday": "December 27th[2]",
      "Bounty": "At least100,000[3]",
      "Japanese Voice": "Shinobu Satouchi"
    },
    {
      "source_name": "Lip_Doughty",
      "source_url": "https://onepiece.fandom.com/wiki/Lip_Doughty",
      "Japanese Name": "リップ・ドウティ",
      "Romanized Name": "Rippu Douti",
      "Official English Name": "Lip Doughty[1]",
      "Debut": "Chapter 600;Episode 519[1]",
      "Affiliations": "Fake Straw Hat Crew;[1]His own crew[1]",
      "Occupations": "Pirate;Captain[1]",
      "Epithet": "Lip \"Service\" Doughty(リップ・\"サービス\"・ドウティ,Rippu Sābisu Douti?)[1]",
      "Status": "Alive",
      "Bounty": "88,000,000[1]",
      "Japanese Voice": "Shinichi Yamada",
      "English Voice": "Funimation:Christopher Wehkamp"
    },
    {
      "source_name": "Little_Oars_Jr.",
      "source_url": "https://onepiece.fandom.com/wiki/Little_Oars_Jr.",
      "Japanese Name": "リトルオーズJr.",
      "Romanized Name": "Ritoru Ōzu Junia",
      "Official English Name": "Little Oars Jr.",
      "Debut": "Chapter 554;Episode 463[1]",
      "Affiliations": "Little Pirates;[2]Subordinate of theWhitebeard Pirates[1]",
      "Occupations": "Pirate Captain[2]",
      "Origin": "Grand Line[2]",
      "Status": "Unknown",
      "Age": "70 (debut)72 (after timeskip)[2]",
      "Birthday": "February 12th[3]",
      "Height": "60 m (196'10\")[4]",
      "Blood Type": "F[2]",
      "Bounty": "550,000,000[2]",
      "Japanese Voice": "Keiji Hirai",
      "English Voice": "Funimation:Jeremy Schwartz"
    },
    {
      "source_name": "Lord_of_the_Coast",
      "source_url": "https://onepiece.fandom.com/wiki/Lord_of_the_Coast",
      "Japanese Name": "近海の主",
      "Romanized Name": "Kinkai no Nushi",
      "Official English Name": "\"Local Sea Monster\";[1]Master of the Near Sea(video games);Lord of the Coast(live-action series,[2]OPCG)",
      "Debut": "Chapter 1;Episode 4[3]",
      "Occupations": "Foosha Village's localSea King",
      "Origin": "East Blue[4]",
      "Status": "Alive",
      "Birthday": "September 14th[5]",
      "English Voice": "Funimation:Nasim Benelkour"
    },
    {
      "source_name": "Macro_(Automaton)",
      "source_url": "https://onepiece.fandom.com/wiki/Macro_(Automaton)",
      "Japanese Name": "マクロ大佐",
      "Romanized Name": "Makuro Taisa",
      "Official English Name": "Macro",
      "Debut": "Chapter 437(cover)[1]",
      "Affiliations": "Automata",
      "Occupations": "Colonel",
      "Status": "Alive"
    },
    {
      "source_name": "Maha",
      "source_url": "https://onepiece.fandom.com/wiki/Maha",
      "Japanese Name": "マハ",
      "Romanized Name": "Maha",
      "Official English Name": "Maha",
      "Debut": "Chapter 929;Episode 922[1]",
      "Affiliations": "CP0[1]",
      "Occupations": "Cipher PolAgent[1]",
      "Status": "Unknown",
      "Japanese Voice": "Takuro Nakakuni[2]",
      "English Voice": "Funimation:Chris Niosi"
    },
    {
      "source_name": "Maidy",
      "source_url": "https://onepiece.fandom.com/wiki/Maidy",
      "Japanese Name": "メイディ",
      "Romanized Name": "Meidi",
      "Official English Name": "Maidy[1]",
      "Debut": "Chapter 215;Episode 129[2]",
      "Affiliations": "Nefertari Family[2]",
      "Occupations": "Lady's maid[2]",
      "Residence": "Alubarna,Arabasta[2]",
      "Status": "Alive",
      "Japanese Voice": "Masumi Kageyama (Episode 129);Ai Kawashima(Movie 8)"
    },
    {
      "source_name": "Maki",
      "source_url": "https://onepiece.fandom.com/wiki/Maki",
      "Japanese Name": "マキ",
      "Romanized Name": "Maki",
      "Debut": "Chapter 925;Episode 917[1]",
      "Affiliations": "Blackbeard Pirates",
      "Status": "Alive"
    },
    {
      "source_name": "Makino's_Child",
      "source_url": "https://onepiece.fandom.com/wiki/Makino's_Child",
      "Japanese Name": "マキノの子",
      "Romanized Name": "Makino no Ko",
      "Debut": "Chapter 614;[1]Episode 878[2]",
      "Origin": "East Blue(Foosha Village)[3]",
      "Status": "Alive",
      "Age": "0–1[3]",
      "English Voice": "Funimation:Sara Ragsdale"
    },
    {
      "source_name": "Manjaro",
      "source_url": "https://onepiece.fandom.com/wiki/Manjaro",
      "Japanese Name": "マンジャロウ",
      "Romanized Name": "Manjarō",
      "Official English Name": "Manjaro[1]",
      "Debut": "Chapter 598;Episode 518[2]",
      "Affiliations": "Fake Straw Hat Crew[2]",
      "Occupations": "Pirate[2]",
      "Origin": "East Blue[3]",
      "Status": "Alive",
      "Age": "25[3]",
      "Birthday": "September 9th[3]",
      "Height": "202 cm (6'7\")[3]",
      "Blood Type": "S[3]",
      "Japanese Voice": "Kappei Yamaguchi",
      "English Voice": "Funimation:Sonny Strait"
    },
    {
      "source_name": "Margarita",
      "source_url": "https://onepiece.fandom.com/wiki/Margarita",
      "Japanese Name": "マルガリータ",
      "Romanized Name": "Marugarīta",
      "Official English Name": "Margarita",
      "Debut": "Chapter 483;Episode 375[1]",
      "Affiliations": "Egana[1]",
      "Occupations": "Maid",
      "Status": "Alive",
      "Japanese Voice": "Houko Kuwashima",
      "English Voice": "Funimation:Jamie Marchi"
    },
    {
      "source_name": "Maria_Napole",
      "source_url": "https://onepiece.fandom.com/wiki/Maria_Napole",
      "Japanese Name": "マリア・ナポレ",
      "Romanized Name": "Maria Napore",
      "Official English Name": "Maria Napole",
      "Debut": "Chapter 649;Episode 569[1]",
      "Affiliations": "Fish-Man Island[1]",
      "Occupations": "Singer[1]",
      "Origin": "Grand Line(Ryugu Kingdom;Fish-Man Island)",
      "Residence": "Ryugu Kingdom",
      "Status": "Alive",
      "Japanese Voice": "Kumiko Mori"
    },
    {
      "source_name": "Marianne",
      "source_url": "https://onepiece.fandom.com/wiki/Marianne",
      "Japanese Name": "マリアンヌ",
      "Romanized Name": "Mariannu",
      "Official English Name": "Marianne[1]",
      "Debut": "Chapter 117;Episode 70[2]",
      "Affiliations": "New Spiders Cafe;[3]Baroque Works[4](former)",
      "Occupations": "Cafe Employee;[3]Officer Agent[4](former)",
      "Origin": "North Blue[5]",
      "Alias": "\"Miss Goldenweek\"(ミス・ゴールデンウィーク,Misu Gōruden Wīku?, Odex/Funimation: \"Miss Golden Week\"; 4Kids: \"Ms. April Fools Day\")[4]",
      "Epithet": "\"Flag-Bearer of Freedom\"(自由の旗手マリアンヌ,Jiyū no Kishu Mariannu?)[5]",
      "Status": "Alive",
      "Age": "16 (debut)18 (after timeskip)[5]",
      "Birthday": "April 29th[6]",
      "Height": "145 cm (4'9\")[5]",
      "Blood Type": "XF[5]",
      "Bounty": "29,000,000[5]",
      "Japanese Voice": "Akiko Nakagawa",
      "English Voice": "Odex:Cindy CreekmoreFunimation:Cherami Leigh",
      "Live-Action Portrayal": "Sophia Anne Caruso"
    },
    {
      "source_name": "Marilyn",
      "source_url": "https://onepiece.fandom.com/wiki/Marilyn",
      "Japanese Name": "マリリン",
      "Romanized Name": "Maririn",
      "Official English Name": "Marilyn",
      "Debut": "Chapter 300;Episode 193[1]",
      "Affiliations": "Neutral civilian",
      "Occupations": "Miss Skypiea (former)",
      "Status": "Alive",
      "Japanese Voice": "N/A"
    },
    {
      "source_name": "Marin",
      "source_url": "https://onepiece.fandom.com/wiki/Marin",
      "Japanese Name": "マリン",
      "Romanized Name": "Marin",
      "Official English Name": "Marin",
      "Debut": "Chapter 500;Episode 394[1]",
      "Occupations": "Slave[1]",
      "Origin": "Grand Line(Sabaody Archipelago)[2]",
      "Residence": "Sabaody Archipelago",
      "Status": "Alive",
      "Birthday": "October 17th[2]",
      "Japanese Voice": "Yasunori Masutani",
      "English Voice": "Funimation:Brian Hathaway"
    },
    {
      "source_name": "Mario",
      "source_url": "https://onepiece.fandom.com/wiki/Mario",
      "Japanese Name": "マリオ",
      "Romanized Name": "Mario",
      "Official English Name": "Mario",
      "Debut": "Chapter 701;Episode 630[1]",
      "Status": "Alive"
    },
    {
      "source_name": "Marlon",
      "source_url": "https://onepiece.fandom.com/wiki/Marlon",
      "Japanese Name": "マーロン",
      "Romanized Name": "Māron",
      "Official English Name": "Marlon",
      "Debut": "Chapter 1155[1]",
      "Affiliations": "Rocks Pirates[1]",
      "Occupations": "Pirate; Gangster[1]",
      "Origin": "West Blue[1]",
      "Residence": "Hachinosu[2]",
      "Epithet": "\"Don Marlon\"(首領・マーロン,Don Māron?)[1]",
      "Status": "Deceased"
    },
    {
      "source_name": "Marumieta",
      "source_url": "https://onepiece.fandom.com/wiki/Marumieta",
      "Japanese Name": "マルミエータ",
      "Romanized Name": "Marumiēta",
      "Official English Name": "Marmieta",
      "Debut": "Chapter 436[1]",
      "Residence": "Pucci[2]",
      "Status": "Alive"
    },
    {
      "source_name": "Mashikaku_(Marine)",
      "source_url": "https://onepiece.fandom.com/wiki/Mashikaku_(Marine)",
      "Japanese Name": "マシカク",
      "Romanized Name": "Mashikaku",
      "Official English Name": "Mashikaku",
      "Debut": "Chapter 98;Episode 48[1]",
      "Affiliations": "Marines[1];Loguetown Marine Base",
      "Occupations": "MarineChief Petty Officer",
      "Origin": "East Blue[2]",
      "Residence": "Loguetown",
      "Status": "Alive",
      "Birthday": "December 26th[2]",
      "Bounty": "At least100,000[3]",
      "Japanese Voice": "Masaya Takatsuka",
      "English Voice": "Funimation:J. Michael Tatum",
      "Live-Action Portrayal": "Fadzai Simango"
    },
    {
      "source_name": "Masked_Deuce",
      "source_url": "https://onepiece.fandom.com/wiki/Masked_Deuce",
      "Japanese Name": "マスクド・デュース",
      "Romanized Name": "Masukudo Dyūsu",
      "Official English Name": "Masked Deuce",
      "Debut": "Chapter 552;Episode 461[1]",
      "Affiliations": "Spade Pirates;[2]Whitebeard Pirates",
      "Occupations": "Journalist;Pirate(former);Doctor(former);Explorer(former)",
      "Status": "Alive"
    },
    {
      "source_name": "Master",
      "source_url": "https://onepiece.fandom.com/wiki/Master",
      "Japanese Name": "親方",
      "Romanized Name": "Oyakata",
      "Official English Name": "Boss",
      "Debut": "Chapter 233;Episode 145[1]",
      "Occupations": "Digger[1]",
      "Status": "Alive"
    },
    {
      "source_name": "Master_of_the_Waters",
      "source_url": "https://onepiece.fandom.com/wiki/Master_of_the_Waters",
      "Japanese Name": "海の主",
      "Romanized Name": "Umi no Nushi",
      "Debut": "Chapter 319;Episode 227[1]",
      "Occupations": "Sea King",
      "Status": "Unknown"
    },
    {
      "source_name": "Matryo_Princesses",
      "source_url": "https://onepiece.fandom.com/wiki/Matryo_Princesses",
      "Japanese Name": "マトリョー姫達",
      "Romanized Name": "Matoryō Hime-tachi",
      "Official English Name": "Mattryoshesses",
      "Debut": "Chapter 905;Episode 882[1]",
      "Occupations": "Princessesof theRoshwan Kingdom[1]",
      "Residence": "Roshwan Kingdom[1]",
      "Status": "Alive"
    },
    {
      "source_name": "Matsuge",
      "source_url": "https://onepiece.fandom.com/wiki/Matsuge",
      "Japanese Name": "睫毛（マツゲ）",
      "Romanized Name": "Matsuge",
      "Official English Name": "Eyelashes (Viz),Eyelash (4Kids, FUNimation dub),Lashes (FUNimation subs),Matsuge (WT100)",
      "Debut": "Chapter 162;[1]Episode 93[2]",
      "Affiliations": "Super Spot-Billed Duck Troops[3]",
      "Occupations": "Royal Transport",
      "Origin": "Grand Line(Arabasta Kingdom)[4]",
      "Residence": "Alubarna;Rainbase(former)",
      "Status": "Alive",
      "Age": "15 (debut)17 (after timeskip)[4]",
      "Birthday": "August 17th[4]",
      "Height": "190 cm (6'3\")[4]",
      "Blood Type": "F[4]",
      "Japanese Voice": "Kappei Yamaguchi",
      "English Voice": "4Kids:Jamie McGonnigalFunimation:Mike McFarland;Troy Baker(Episode of Arabasta: The Desert Princess and the Pirates)"
    },
    {
      "source_name": "MAX_Marx",
      "source_url": "https://onepiece.fandom.com/wiki/MAX_Marx",
      "Japanese Name": "MAXマークス",
      "Romanized Name": "Makkusu Mākusu",
      "Official English Name": "Max Marx",
      "Debut": "Chapter 966;Episode 967[1]",
      "Affiliations": "Roger Pirates[1]",
      "Occupations": "Pirate;Cook[2]",
      "Status": "Unknown"
    },
    {
      "source_name": "Mayushika",
      "source_url": "https://onepiece.fandom.com/wiki/Mayushika",
      "Japanese Name": "マユシカ",
      "Romanized Name": "Mayushika",
      "Official English Name": "Mayushka[1]",
      "Debut": "Chapter 269;Episode 176[2]",
      "Affiliations": "Shandia[2]",
      "Occupations": "ShandiaWarrior[2]",
      "Status": "Alive",
      "Japanese Voice": "Masashi Hamano"
    },
    {
      "source_name": "McKinley",
      "source_url": "https://onepiece.fandom.com/wiki/McKinley",
      "Japanese Name": "マッキンリー",
      "Romanized Name": "Makkinrī",
      "Official English Name": "McKinley",
      "Debut": "Chapter 241;Episode 155[1]",
      "Affiliations": "God's Guards[1]",
      "Occupations": "Law enforcement official[1]",
      "Status": "Alive",
      "Japanese Voice": "Keiichi Sonobe",
      "English Voice": "Funimation:Jim Johnson"
    },
    {
      "source_name": "Mecha-Shark",
      "source_url": "https://onepiece.fandom.com/wiki/Mecha-Shark",
      "Japanese Name": "メカシャーク",
      "Romanized Name": "Mekashāku",
      "Official English Name": "Mecha-Shark",
      "Debut": "Chapter 1061;Episode 1089[1]",
      "Affiliations": "Vegapunk[1]",
      "Residence": "Egghead[1]",
      "Status": "Unknown"
    },
    {
      "source_name": "Mero",
      "source_url": "https://onepiece.fandom.com/wiki/Mero",
      "Japanese Name": "メロ",
      "Romanized Name": "Mero",
      "Official English Name": "Mello (Viz); Mero (FUNimation)",
      "Debut": "Chapter 608;Episode 527[1]",
      "Affiliations": "Mermaid Cafe",
      "Occupations": "Dancer",
      "Origin": "Grand Line(Ryugu Kingdom;Fish-Man Island)",
      "Residence": "Mermaid Cove(Coral Hill)",
      "Status": "Alive",
      "Japanese Voice": "Unknown",
      "English Voice": "Funimation:Skyler Davenport"
    },
    {
      "source_name": "Merry",
      "source_url": "https://onepiece.fandom.com/wiki/Merry",
      "Japanese Name": "メリー",
      "Romanized Name": "Merī",
      "Official English Name": "Merry",
      "Debut": "Chapter 24;Episode 11[1]",
      "Affiliations": "Kaya",
      "Occupations": "Butler",
      "Origin": "East Blue(Syrup Village)[2]",
      "Residence": "Syrup Village",
      "Status": "Alive",
      "Birthday": "January 22nd[3][2]",
      "Japanese Voice": "Jin Domon",
      "English Voice": "Odex:Chuck Powers4Kids:Ted LewisFunimation:Jerry Jewell",
      "Live-Action Portrayal": "Brett Williams"
    },
    {
      "source_name": "Mezasuzowan_Pisuo",
      "source_url": "https://onepiece.fandom.com/wiki/Mezasuzowan_Pisuo",
      "Japanese Name": "メザスゾワン・ピースオ",
      "Romanized Name": "Mezasuzowan Pīsuo",
      "Debut": "Chapter 963[1]",
      "Affiliations": "Germ Pirates[1]",
      "Occupations": "Pirate[1]",
      "Status": "Alive"
    }
  ]
}